README.rst
setup.py
Yinotify/__init__.py
Yinotify/adapters.py
Yinotify/calls.py
Yinotify/constants.py
Yinotify/library.py
Yinotify.egg-info/PKG-INFO
Yinotify.egg-info/SOURCES.txt
Yinotify.egg-info/dependency_links.txt
Yinotify.egg-info/top_level.txt
Yinotify.egg-info/zip-safe
tests/monDIR/__init__.py